myers.py
myers-1.0.1.data/scripts/myers.py
myers-1.0.1.dist-info/LICENSE
myers-1.0.1.dist-info/METADATA
myers-1.0.1.dist-info/WHEEL
myers-1.0.1.dist-info/top_level.txt
myers-1.0.1.dist-info/RECORD
